elepay/__init__.py
elepay/api_client.py
elepay/configuration.py
elepay/exceptions.py
elepay/rest.py
elepay/schemas.py
elepay/apis/__init__.py
elepay/apis/path_to_api.py
elepay/apis/tag_to_api.py
elepay/apis/paths/__init__.py
elepay/apis/paths/charges.py
elepay/apis/paths/charges_id.py
elepay/apis/paths/charges_id_capture.py
elepay/apis/paths/charges_id_refunds.py
elepay/apis/paths/charges_id_refunds_refund_id.py
elepay/apis/paths/charges_id_revoke.py
elepay/apis/paths/charges_id_status.py
elepay/apis/paths/code_setting_payment_methods.py
elepay/apis/paths/codes.py
elepay/apis/paths/codes_code_id.py
elepay/apis/paths/customers.py
elepay/apis/paths/customers_customer_id.py
elepay/apis/paths/customers_customer_id_sources.py
elepay/apis/paths/customers_customer_id_sources_source_id.py
elepay/apis/paths/disputes.py
elepay/apis/paths/disputes_id.py
elepay/apis/paths/invoices.py
elepay/apis/paths/invoices_invoice_id.py
elepay/apis/paths/invoices_invoice_id_cancel.py
elepay/apis/paths/invoices_invoice_id_send.py
elepay/apis/paths/invoices_invoice_id_submit.py
elepay/apis/paths/payment_methods.py
elepay/apis/paths/sources_source_id_status.py
elepay/apis/paths/subscriptions.py
elepay/apis/paths/subscriptions_subscription_id.py
elepay/apis/paths/subscriptions_subscription_id_cancel.py
elepay/apis/paths/subscriptions_subscription_id_periods.py
elepay/apis/paths/subscriptions_subscription_id_resume.py
elepay/apis/paths/subscriptions_subscription_id_start.py
elepay/apis/paths/terminal_locations.py
elepay/apis/paths/terminal_readers.py
elepay/apis/paths/terminal_readers_reader_id.py
elepay/apis/tags/__init__.py
elepay/apis/tags/charge_api.py
elepay/apis/tags/code_api.py
elepay/apis/tags/code_setting_api.py
elepay/apis/tags/customer_api.py
elepay/apis/tags/dispute_api.py
elepay/apis/tags/invoice_api.py
elepay/apis/tags/payment_method_api.py
elepay/apis/tags/refund_api.py
elepay/apis/tags/subscription_api.py
elepay/apis/tags/terminal_api.py
elepay/model/__init__.py
elepay_python_sdk-1.2.0.dist-info/METADATA
elepay_python_sdk-1.2.0.dist-info/WHEEL
elepay_python_sdk-1.2.0.dist-info/top_level.txt
elepay_python_sdk-1.2.0.dist-info/RECORD
