Metadata-Version: 2.1
Name: elepay-python-sdk
Version: 1.2.0
Summary: elepay API リファレンス
Home-page: https://github.com/elestyle/elepay-python-sdk
Author: ELESTYLE, INC
Author-email: support@elestyle.jp
Keywords: restful,elepay API リファレンス
Requires-Python: >=3.7
Requires-Dist: certifi (>=14.5.14)
Requires-Dist: frozendict (~=2.3.4)
Requires-Dist: python-dateutil (~=2.7.0)
Requires-Dist: setuptools (>=21.0.0)
Requires-Dist: typing-extensions (~=4.3.0)
Requires-Dist: urllib3 (~=1.26.7)
